{
  "version": "7",
  "dialect": "postgresql",
  "entries": [
    {
      "idx": 0,
      "version": "7",
      "when": 1780282671741,
      "tag": "0000_create_initial_tables",
      "breakpoints": true
    },
    {
      "idx": 1,
      "version": "7",
      "when": 1780284731573,
      "tag": "0001_add_binders_table",
      "breakpoints": true
    },
    {
      "idx": 2,
      "version": "7",
      "when": 1780290175908,
      "tag": "0002_remove_tag_name_unique_constraint",
      "breakpoints": true
    }
  ]
}